MANIFEST.in
README.rst
pyproject.toml
setup.cfg
setup.py
development/__init__.py
development/admin.py
development/apps.py
development/forms.py
development/models.py
development/tests.py
development/urls.py
development/views.py
development/migrations/__init__.py
development/templates/activity/add.html
development/templates/activity/add1.html
development/templates/activity/detail.html
development/templates/activity/list.html
development/templates/custom/agency_form.html
development/templates/custom/agency_list.html
development/templates/custom/company_form.html
development/templates/custom/company_list.html
development/templates/custom/dependent_select.html
development/templates/custom/national_form.html
development/templates/custom/national_list.html
development/templates/custom/ong_form.html
development/templates/custom/ong_list.html
development/templates/development/dashboard_development.html
development/templates/development/sidebar.html
development/templates/fund/fundactivityadd.html
development/templates/fund/fundlist.html
development/templates/fund/fundprojectadd.html
development/templates/project/add.html
development/templates/project/add1.html
development/templates/project/detail.html
development/templates/project/list.html
development/templates/reports/report_dashboard.html
development/templates/reports/print/activity.html
development/templates/reports/print/project.html
development/views/__init__.py
development/views/activity.py
development/views/custom.py
development/views/fund.py
development/views/project.py
development/views/report.py
docs/info.txt
maetl_development.egg-info/PKG-INFO
maetl_development.egg-info/SOURCES.txt
maetl_development.egg-info/dependency_links.txt
maetl_development.egg-info/requires.txt
maetl_development.egg-info/top_level.txt